[{"id":"vintage-theme","name":"Vintage Theme","added_commit":{"date":{"year":2022,"month":2,"day":3},"hash":"182986d0320c0819c71bf0de9c3a4d5bb716995e"},"removed_commit":{"date":{"year":2024,"month":9,"day":14},"hash":"778018dce5cffe75f8b30bf6e534b8ef196daeaf"},"initial_entry":{"name":"Vintage Theme","author":"natelandau","repo":"natelandau/obsidian-vintage-theme","screenshot":"_media/light.png","modes":["dark","light"],"legacy":false},"current_entry":{"name":"Vintage Theme","author":"natelandau","repo":"natelandau/obsidian-vintage-theme","screenshot":"_media/light.png","modes":["dark","light"],"legacy":true},"change_history":[{"property":"Theme Added","commit":{"date":{"year":2022,"month":2,"day":3},"hash":"182986d0320c0819c71bf0de9c3a4d5bb716995e"},"old_value":"","new_value":""},{"property":"Theme Removed","commit":{"date":{"year":2024,"month":9,"day":14},"hash":"778018dce5cffe75f8b30bf6e534b8ef196daeaf"},"old_value":"","new_value":""}]},{"id":"vesnea-vibe","name":"Vesnea Vibe","added_commit":{"date":{"year":2025,"month":9,"day":10},"hash":"d8a441101ad932f79ef5e00a6dc16dfc0431c281"},"removed_commit":null,"initial_entry":{"name":"Vesnea Vibe","author":"Seavalanche","repo":"seavalanche/vesnea-obsidian-theme","screenshot":"store-display.png","modes":["dark","light"],"legacy":false},"current_entry":{"name":"Vesnea Vibe","author":"Seavalanche","repo":"seavalanche/vesnea-obsidian-theme","screenshot":"store-display.png","modes":["dark","light"],"legacy":false},"change_history":[{"property":"Theme Added","commit":{"date":{"year":2025,"month":9,"day":10},"hash":"d8a441101ad932f79ef5e00a6dc16dfc0431c281"},"old_value":"","new_value":""}]},{"id":"oreo","name":"Oreo","added_commit":{"date":{"year":2024,"month":7,"day":20},"hash":"4fb759307df80778f26acfdfbb3f9acd9719997f"},"removed_commit":null,"initial_entry":{"name":"Oreo","author":"carols12352","repo":"carols12352/Oreo-theme","screenshot":"images/thumbnail.png","modes":["light","dark"],"legacy":false},"current_entry":{"name":"Oreo","author":"carols12352","repo":"carols12352/Oreo-theme","screenshot":"images/thumbnail.png","modes":["light","dark"],"legacy":false},"change_history":[{"property":"Theme Added","commit":{"date":{"year":2024,"month":7,"day":20},"hash":"4fb759307df80778f26acfdfbb3f9acd9719997f"},"old_value":"","new_value":""},{"property":"Theme Removed","commit":{"date":{"year":2024,"month":5,"day":18},"hash":"e87a00fc8f0ad5d912750c7bab79d48fed79c302"},"old_value":"","new_value":""},{"property":"Theme Readded","commit":{"date":{"year":2024,"month":12,"day":7},"hash":"6baab2c039ffec82352b07159fd640fca01f0ee1"},"old_value":"","new_value":""}]},{"id":"80s-neon","name":"80s Neon","added_commit":{"date":{"year":2020,"month":11,"day":24},"hash":"7d4a5b83b126da51e8784de0e8022ea4b67da023"},"removed_commit":null,"initial_entry":{"name":"80s Neon","author":"deathau","repo":"deathau/80s-Neon-for-Obsidian.md","screenshot":"screenshot.jpg","modes":["dark","light"],"legacy":false},"current_entry":{"name":"80s Neon","author":"deathau","repo":"deathau/80s-Neon-for-Obsidian.md","screenshot":"screenshot.jpg","modes":["dark","light"],"legacy":false},"change_history":[{"property":"Theme Added","commit":{"date":{"year":2020,"month":11,"day":24},"hash":"7d4a5b83b126da51e8784de0e8022ea4b67da023"},"old_value":"","new_value":""}]},{"id":"everforest-enchanted","name":"Everforest Enchanted","added_commit":{"date":{"year":2023,"month":3,"day":22},"hash":"84ff4a52f9d81b7ca74734c130e20036e5c90b04"},"removed_commit":null,"initial_entry":{"name":"Everforest Enchanted","author":"FireIsGood","repo":"FireIsGood/obsidian-everforest-enchanted","screenshot":"promo_screenshot.png","modes":["dark","light"],"legacy":false},"current_entry":{"name":"Everforest Enchanted","author":"FireIsGood","repo":"FireIsGood/obsidian-everforest-enchanted","screenshot":"promo_screenshot.png","modes":["dark","light"],"legacy":false},"change_history":[{"property":"Theme Added","commit":{"date":{"year":2023,"month":3,"day":22},"hash":"84ff4a52f9d81b7ca74734c130e20036e5c90b04"},"old_value":"","new_value":""}]},{"id":"midnight","name":"Midnight","added_commit":{"date":{"year":2024,"month":5,"day":11},"hash":"d51127d1d51e0a5984491473ef35fe3fd6ef1f62"},"removed_commit":{"date":{"year":2025,"month":2,"day":26},"hash":"74028dc6aec2797cea3118fea508b7d1a253c447"},"initial_entry":{"name":"Midnight","author":"SemiCirkle","repo":"SemiCirkle/Midnight-obsidian-theme","screenshot":"pictures/theme-preview-512x288.png","modes":["dark"],"legacy":false},"current_entry":{"name":"Midnight","author":"SemiCirkle","repo":"SemiCirkle/Midnight-obsidian-theme","screenshot":"pictures/theme-preview-512x288.png","modes":["dark"],"legacy":false},"change_history":[{"property":"Theme Added","commit":{"date":{"year":2024,"month":5,"day":11},"hash":"d51127d1d51e0a5984491473ef35fe3fd6ef1f62"},"old_value":"","new_value":""},{"property":"Theme Removed","commit":{"date":{"year":2025,"month":2,"day":26},"hash":"74028dc6aec2797cea3118fea508b7d1a253c447"},"old_value":"","new_value":""}]},{"id":"cocoa","name":"cocoa","added_commit":{"date":{"year":2025,"month":4,"day":11},"hash":"9ca556d22d324482b4e66c35655f01cf4683ffb6"},"removed_commit":{"date":{"year":2025,"month":10,"day":21},"hash":"7c1d8609d4881d22b57d81da4a68058f81508776"},"initial_entry":{"name":"cocoa","author":"incantatem2","repo":"incantatem2/Obsidian-cocoa","screenshot":"images/cocoa-thumbnail.jpg","modes":["dark"],"legacy":false},"current_entry":{"name":"cocoa","author":"incantatem2","repo":"incantatem2/Obsidian-cocoa","screenshot":"images/cocoa-thumbnail.jpg","modes":["dark"],"legacy":false},"change_history":[{"property":"Theme Added","commit":{"date":{"year":2025,"month":4,"day":11},"hash":"9ca556d22d324482b4e66c35655f01cf4683ffb6"},"old_value":"","new_value":""},{"property":"Theme Removed","commit":{"date":{"year":2025,"month":10,"day":21},"hash":"7c1d8609d4881d22b57d81da4a68058f81508776"},"old_value":"","new_value":""}]},{"id":"dust","name":"Dust","added_commit":{"date":{"year":2025,"month":4,"day":15},"hash":"cb10f56f8aff73b98f1e588fa8a6bb0788d0dca5"},"removed_commit":null,"initial_entry":{"name":"Dust","author":"ph17","repo":"ph17/Dust","screenshot":"theme_screenshot.png","modes":["dark"],"legacy":false},"current_entry":{"name":"Dust","author":"ph17","repo":"ph17/Dust","screenshot":"theme_screenshot.png","modes":["dark"],"legacy":false},"change_history":[{"property":"Theme Added","commit":{"date":{"year":2025,"month":4,"day":15},"hash":"cb10f56f8aff73b98f1e588fa8a6bb0788d0dca5"},"old_value":"","new_value":""}]},{"id":"olivier-s-theme","name":"Olivier’s Theme","added_commit":{"date":{"year":2023,"month":4,"day":18},"hash":"c635b26bef8f5035f03e8bda166b36d9bdee31bc"},"removed_commit":null,"initial_entry":{"name":"Olivier’s Theme","author":"Olivier Spinnler","repo":"OlivierPS/Olivier-s-Theme","screenshot":"main-screenshot.png","modes":["dark","light"],"legacy":false},"current_entry":{"name":"Olivier’s Theme","author":"Olivier Spinnler","repo":"OlivierPS/Olivier-s-Theme","screenshot":"main-screenshot.png","modes":["dark","light"],"legacy":false},"change_history":[{"property":"Theme Added","commit":{"date":{"year":2023,"month":4,"day":18},"hash":"c635b26bef8f5035f03e8bda166b36d9bdee31bc"},"old_value":"","new_value":""}]},{"id":"pisum","name":"Pisum","added_commit":{"date":{"year":2020,"month":11,"day":24},"hash":"7d4a5b83b126da51e8784de0e8022ea4b67da023"},"removed_commit":null,"initial_entry":{"name":"Pisum","author":"MooddooM","repo":"GuangluWu/obsidian-pisum","screenshot":"fullpower.png","modes":["dark"],"legacy":false},"current_entry":{"name":"Pisum","author":"MooddooM","repo":"GuangluWu/obsidian-pisum","screenshot":"fullpower.png","modes":["dark"],"legacy":false},"change_history":[{"property":"Theme Added","commit":{"date":{"year":2020,"month":11,"day":24},"hash":"7d4a5b83b126da51e8784de0e8022ea4b67da023"},"old_value":"","new_value":""}]},{"id":"evilred","name":"EvilRed","added_commit":{"date":{"year":2023,"month":11,"day":8},"hash":"cc658b7b7f5bd522769c6165f685d7633ab3442f"},"removed_commit":null,"initial_entry":{"name":"EvilRed","author":"Atmanand Gauns","repo":"tu2-atmanand/EvilRed-ObsidianTheme","screenshot":"Thumbnail.png","modes":["dark"],"legacy":false},"current_entry":{"name":"EvilRed","author":"Atmanand Gauns","repo":"tu2-atmanand/EvilRed-ObsidianTheme","screenshot":"Thumbnail.png","modes":["dark"],"legacy":false},"change_history":[{"property":"Theme Added","commit":{"date":{"year":2023,"month":11,"day":8},"hash":"cc658b7b7f5bd522769c6165f685d7633ab3442f"},"old_value":"","new_value":""}]}]