{"id":"autoplay-and-loop","repo":{"uses_typescript":true,"has_package_json":true,"package_managers":[],"testing_frameworks":[],"bundlers":["ESBuild"],"dependencies":[],"dev_dependencies":["@types/node","@typescript-eslint/eslint-plugin","@typescript-eslint/parser","builtin-modules","esbuild","obsidian","tslib","typescript"],"has_test_files":false,"has_beta_manifest":false,"file_type_counts":{"ts":1,"LICENSE":1,"json":5,"mjs":1,"gitignore":1,"md":1},"package_json_license":"GPL-3.0-only","license_file":"unknown","manifest":{"author":"Zerkshop & Wapply","minAppVersion":"1.5.11","name":"Autoplay & Loop","version":"1.0.1","authorUrl":"https://github.com/Wapply","fundingUrl":{"Buy Me a Coffee":"https://ko-fi.com/wapply"},"description":"Auto reproduces videos/audio inside notes.","id":"autoplay-and-loop","isDesktopOnly":false,"helpUrl":null}},"warnings":[],"removal_reason":null,"deprecated_versions":[]}