{"id":"custom-image-auto-uploader","repo":{"usesTypescript":true,"hasPackageJson":true,"packageManager":"pnpm","dependencies":["file-type","image-type","react","react-dom"],"devDependencies":["@types/node","@types/react","@types/react-dom","@typescript-eslint/eslint-plugin","@typescript-eslint/parser","builtin-modules","esbuild","obsidian","tslib","typescript"],"installedTestingFrameworks":[],"installedBundlers":["esbuild"],"hasTestFiles":false,"hasBetaManifest":false,"fileCounts":{"md":2,"json":4,"css":1,"mjs":1,"node-version":1,"yml":1,"ts":36,"tsx":3,"scss":1,"gitignore":1,"yaml":1},"license":"MIT","licenseFile":"MIT","manifest":{"id":"custom-image-auto-uploader","name":"Custom Image Auto Uploader","version":"2.5.1","minAppVersion":"1.6.5","description":"You can upload and save images from your notes to your remote server, home NAS, or sync them to your cloud storage (Alibaba Cloud OSS, Amazon S3, Cloudflare R2).","author":"HaierKeys","authorUrl":"https://blog.diybeta.com","isDesktopOnly":false,"fundingUrl":"https://ko-fi.com/haierkeys"}},"warnings":[],"deprecatedVersions":[]}