{"id":"dictionary-translator","repo":{"usesTypescript":true,"hasPackageJson":true,"dependencies":["adm-zip","axios","crypto-js","esbuild-plugin-copy","esbuild-plugin-vue3","js-audio-recorder","jsonp","lucide","lucide-vue-next","mustache"],"devDependencies":["@types/crypto-js","@types/jsonp","@types/mustache","@types/node","@typescript-eslint/eslint-plugin","@typescript-eslint/parser","builtin-modules","esbuild","eslint","eslint-plugin-vue","naive-ui","obsidian","tslib","typescript","vue"],"installedTestingFrameworks":[],"installedBundlers":["esbuild"],"hasTestFiles":false,"hasBetaManifest":false,"fileCounts":{"npmrc":1,"eslintrc":1,"eslintignore":1,"json":7,"css":1,"mjs":2,"md":2,"gif":1,"png":2,"editorconfig":1,"ts":17,"vue":4,"gitignore":1},"license":"MIT","licenseFile":"MIT","manifest":{"id":"dictionary-translator","name":"Dictionary translator","version":"1.0.3","minAppVersion":"1.1.1","description":"It can help you translate words or sentences, listen to recordings of new words or sentences, and even record your own pronunciation to save in the form of internal links to your notes.","author":"Grover","authorUrl":"https://github.com/grover572","isDesktopOnly":false}},"warnings":[{"severity":"caution","id":"mismatched-manifest-data","data":[{"field":"description","manifestValue":"It can help you translate words or sentences, listen to recordings of new words or sentences, and even record your own pronunciation to save in the form of internal links to your notes.","communityListValue":"Helps you to quickly underline word translations and insert word cards in your notes."}]}]}