{"id":"fileorganizer2000","repo":{"uses_typescript":true,"has_package_json":true,"package_managers":["bun","npm","deno","pnpm"],"testing_frameworks":[],"bundlers":["Turbo"],"dependencies":["expo","react","react-markdown","react-native","remark-gfm"],"dev_dependencies":["@types/node","node-gyp","turbo","typescript"],"has_test_files":true,"has_beta_manifest":false,"file_type_counts":{"eslintignore":1,"LICENSE":1,"ttf":1,"env":2,"lock":1,"yaml":4,"cursorrules":2,"icns":1,"txt":1,"sql":23,"example":2,"mjs":5,"toml":1,"svg":8,"eslintrc":1,"avif":1,"Dockerfile":1,"dockerignore":1,"png":30,"yml":6,"md":34,"Fastfile":1,"snap":1,"json":50,"ts":182,"chinese":1,"prettierrc":2,"patch":4,"tsx":294,"pdf":1,"electronignore":1,"mdc":9,"gitignore":8,"ico":5,"lockb":1,"Gemfile":1,"Appfile":1,"js":17,"npmrc":1,"css":7,"jpg":4},"package_json_license":"not set","license_file":"unknown","manifest":{"author":"Benjamin Ashgan Shafii","minAppVersion":"0.15.0","name":"Note Companion (prev. File Organizer 2000)","version":"2.2.1","authorUrl":null,"fundingUrl":null,"description":"An AI assistant to organize and chat with your vault","id":"fileorganizer2000","isDesktopOnly":true,"helpUrl":null}},"warnings":[],"removal_reason":null,"deprecated_versions":[]}