{"id":"flomo-importer","usesTypescript":true,"hasPackageJson":true,"packageManager":"npm","dependencies":["adm-zip","crypto-js","decompress","dompurify","fs-extra","html-parser2","node-html-markdown","node-html-parser","parse5","showdown","turndown","uuid"],"devDependencies":["@types/adm-zip","@types/crypto-js","@types/decompress","@types/dompurify","@types/fs-extra","@types/node","@types/showdown","@types/turndown","@types/uuid","@typescript-eslint/eslint-plugin","@typescript-eslint/parser","builtin-modules","esbuild","gts","obsidian","tslib","typescript"],"installedTestingFrameworks":[],"installedBundlers":["esbuild"],"hasTestFiles":false,"hasBetaManifest":false,"fileCounts":{"ts":7,"json":4,"css":1,"mjs":1,"md":2,"gitignore":1,"png":6,"jpg":4,"jpeg":1},"license":"MIT"}