{"id":"generic-initiative-tracker","usesTypescript":true,"hasPackageJson":true,"packageManager":"npm","dependencies":[],"devDependencies":["@babel/core","@popperjs/core","@rollup/plugin-commonjs","@rollup/plugin-node-resolve","@rollup/plugin-typescript","@tsconfig/svelte","@types/node","babel-loader","copy-webpack-plugin","css-loader","obsidian","rollup","rollup-plugin-css-only","rollup-plugin-svelte","svelte","svelte-loader","svelte-preprocess","title-case","ts-loader","tslib","typescript","webpack","webpack-cli","webpack-node-externals"],"installedTestingFrameworks":[],"installedBundlers":["rollup","webpack"],"hasTestFiles":false,"hasBetaManifest":false,"fileCounts":{"js":1,"gitattributes":1,"json":5,"css":2,"git-blame-ignore-revs":1,"ts":10,"yml":1,"svelte":7,"gitignore":1,"PNG":1,"md":1}}