{"id":"plugin-update-locker","repo":{"usesTypescript":true,"hasPackageJson":true,"dependencies":[],"devDependencies":["@types/node","@typescript-eslint/eslint-plugin","@typescript-eslint/parser","builtin-modules","esbuild","obsidian","tslib","typescript"],"installedTestingFrameworks":[],"installedBundlers":["esbuild"],"hasTestFiles":false,"hasBetaManifest":false,"fileCounts":{"npmrc":1,"png":4,"eslintrc":1,"eslintignore":1,"json":4,"css":1,"mjs":2,"editorconfig":1,"ts":1,"md":2,"gitignore":1},"license":"MIT","licenseFile":"GPL-3.0","manifest":{"id":"plugin-update-locker","name":"Plugin Update Locker","version":"1.0.5","minAppVersion":"1.8.4","description":"Prevent specific plugins from being updated.","author":"Lemon695","authorUrl":"https://github.com/Lemon695","isDesktopOnly":false}},"warnings":[{"severity":"caution","id":"mismatched-manifest-data","data":[{"field":"description","manifestValue":"Prevent specific plugins from being updated.","communityListValue":"Prevent specific plugins from being updated"}]},{"severity":"caution","id":"mismatched-license"}],"deprecatedVersions":[]}