{"id":"recipe-grabber","repo":{"usesTypescript":true,"hasPackageJson":true,"packageManager":"npm","dependencies":["cheerio","dateformat","file-type","handlebars","schema-dts"],"devDependencies":["@eslint/js","@types/dateformat","@types/node","@typescript-eslint/eslint-plugin","@typescript-eslint/parser","builtin-modules","esbuild","eslint","obsidian","prettier","tslib","typescript","typescript-eslint"],"installedTestingFrameworks":[],"installedBundlers":["esbuild"],"hasTestFiles":false,"hasBetaManifest":false,"fileCounts":{"npmrc":1,"eslintrc":2,"eslintignore":1,"prettierrc":1,"mov":1,"json":5,"css":1,"mjs":2,"yml":1,"editorconfig":1,"ts":4,"gitignore":1,"md":1},"license":"MIT","manifest":{"id":"recipe-grabber","name":"Recipe Grabber","version":"0.21.0","minAppVersion":"0.15.0","description":"Quickly grab the important contents of any online recipe.","author":"seethroughdev","authorUrl":"https://github.com/seethroughdev","isDesktopOnly":false}},"warnings":[{"severity":"caution","id":"inactivity-12-months","lastReleaseDate":"2024-06-06"}]}