{"id":"runsh","repo":{"usesTypescript":true,"hasPackageJson":true,"packageManager":"npm","dependencies":[],"devDependencies":["@types/node","@typescript-eslint/eslint-plugin","@typescript-eslint/parser","builtin-modules","esbuild","obsidian","tslib","typescript"],"installedTestingFrameworks":[],"installedBundlers":["esbuild"],"hasTestFiles":false,"hasBetaManifest":false,"fileCounts":{"npmrc":1,"eslintrc":1,"eslintignore":1,"ts":1,"json":5,"mjs":2,"yml":1,"editorconfig":1,"gitignore":1,"md":1},"license":"MIT","licenseFile":"MIT","manifest":{"id":"runsh","name":"Runsh","version":"1.0.4","minAppVersion":"0.15.0","description":"Create buttons that run shell commands from your notes.","author":"Ddone","authorUrl":"https://github.com/Deedone","isDesktopOnly":true}},"warnings":[],"deprecatedVersions":[]}