{"id":"sidebar-resizer","repo":{"uses_typescript":true,"has_package_json":true,"package_managers":["npm","deno"],"testing_frameworks":[],"bundlers":["ESBuild"],"dependencies":[],"dev_dependencies":["@types/node","@typescript-eslint/eslint-plugin","@typescript-eslint/parser","builtin-modules","esbuild","obsidian","tslib","typescript"],"has_test_files":false,"has_beta_manifest":false,"file_type_counts":{"eslintrc":1,"md":2,"npmrc":1,"eslintignore":1,"mjs":2,"css":1,"editorconfig":1,"json":5,"gitignore":1,"yaml":1,"ts":2},"package_json_license":"MIT","license_file":"unknown","manifest":{"author":"Jeet Sukumaran","minAppVersion":"1.4.14","name":"Sidebar Resizer","version":"1.0.11","authorUrl":"https://github/jeetsukumaran/obsidian-sidebar-resizer","fundingUrl":{"Buy Me a Coffee":"https://www.buymeacoffee.com/jeetsukumaran"},"description":"Adjust the sidebar sizes easily.","id":"sidebar-resizer","isDesktopOnly":false,"helpUrl":null}},"warnings":[],"removal_reason":null,"deprecated_versions":[]}